cli_cleaner/__init__.py
cli_cleaner/__main__.py
cli_cleaner/cli.py
cli_cleaner/core.py
cli_cleaner/display.py
cli_cleaner-1.1.dist-info/entry_points.txt
cli_cleaner-1.1.dist-info/LICENSE
cli_cleaner-1.1.dist-info/METADATA
cli_cleaner-1.1.dist-info/WHEEL
cli_cleaner-1.1.dist-info/RECORD
