Metadata-Version: 2.3
Name: CLI_Cleaner
Version: 1.1
Summary: A command-line tool for safely cleaning files and directories using customizable rules and dry-run preview
Author: DasKaroWow
Requires-Python: >=3.10
Classifier: Programming Language :: Python :: 3
Classifier: Programming Language :: Python :: 3.10
Classifier: Programming Language :: Python :: 3.11
Classifier: Programming Language :: Python :: 3.12
Classifier: Programming Language :: Python :: 3.13
Requires-Dist: platformdirs (>=4.3.8)
Requires-Dist: rich (>=14.1.0)
Requires-Dist: typer (>=0.16.0)
Project-URL: Homepage, https://github.com/DasKaroWow/cli_cleaner
Project-URL: Issues, https://github.com/DasKaroWow/cli_cleaner/issues
Project-URL: Source, https://github.com/DasKaroWow/cli_cleaner
